replicate/__about__.py
replicate/__init__.py
replicate/account.py
replicate/client.py
replicate/collection.py
replicate/deployment.py
replicate/exceptions.py
replicate/file.py
replicate/hardware.py
replicate/helpers.py
replicate/identifier.py
replicate/model.py
replicate/pagination.py
replicate/prediction.py
replicate/resource.py
replicate/run.py
replicate/schema.py
replicate/stream.py
replicate/training.py
replicate/version.py
replicate/webhook.py
replicate-1.0.3.dist-info/LICENSE
replicate-1.0.3.dist-info/METADATA
replicate-1.0.3.dist-info/WHEEL
replicate-1.0.3.dist-info/top_level.txt
replicate-1.0.3.dist-info/RECORD
