Metadata-Version: 2.1
Name: replicate
Version: 1.0.3
Summary: Python client for Replicate
Author: Replicate, Inc.
License: 
Project-URL: homepage, https://replicate.com
Project-URL: repository, https://github.com/replicate/replicate-python
Requires-Python: >=3.8
License-File: LICENSE
Requires-Dist: httpx<1,>=0.21.0
Requires-Dist: packaging
Requires-Dist: pydantic>1.10.7
Requires-Dist: typing_extensions>=4.5.0
